LICENSE
MANIFEST.in
README.rst
setup.cfg
setup.py
plowshare/__init__.py
plowshare/hosts.py
plowshare/plowshare.py
plowshare/settings.py
plowshare.egg-info/PKG-INFO
plowshare.egg-info/SOURCES.txt
plowshare.egg-info/dependency_links.txt
plowshare.egg-info/top_level.txt