Metadata-Version: 1.1
Name: plowshare
Version: 0.3.5
Summary: Manages multi-host uploads using plowshare.
Home-page: https://github.com/storj/plowshare-wrapper
Author: Hugo Peixoto
Author-email: hugo.peixoto@gmail.com
License: The MIT License (MIT)
